jxctl/__init__.py
jxctl/clicore.py
jxctl/ctxcore.py
jxctl/jxcore.py
jxctl/jxsupport.py
jxctl-1.0.0.dist-info/LICENSE
jxctl-1.0.0.dist-info/METADATA
jxctl-1.0.0.dist-info/WHEEL
jxctl-1.0.0.dist-info/entry_points.txt
jxctl-1.0.0.dist-info/top_level.txt
jxctl-1.0.0.dist-info/RECORD
