Metadata-Version: 2.1
Name: jxctl
Version: 1.0.0
Summary: A Command line interface for Jenkins
Home-page: https://github.com/deepan10/jxctl
Author: Deepankumar Loganathan
Author-email: deepan0433@gmail.com
License: UNKNOWN
Platform: UNKNOWN
Classifier: Programming Language :: Python :: 3.6
Classifier: Programming Language :: Python :: 3.7
Classifier: Operating System :: OS Independent
Classifier: License :: OSI Approved :: MIT License
Requires-Dist: PyYAML (>=4.2b1)
Requires-Dist: Click (>=7.0)
Requires-Dist: requests (>=2.22.0)
Requires-Dist: tabulate (>=0.8.3)
Requires-Dist: python-jenkins (>=1.4.0)
